README.md
setup.py
geecomposite/__init__.py
geecomposite/_version.py
geecomposite.egg-info/PKG-INFO
geecomposite.egg-info/SOURCES.txt
geecomposite.egg-info/dependency_links.txt
geecomposite.egg-info/requires.txt
geecomposite.egg-info/top_level.txt
geecomposite/widgets/__init__.py
geecomposite/widgets/bap.py
geecomposite/widgets/calendar.py
geecomposite/widgets/clouds.py
geecomposite/widgets/collections.py
geecomposite/widgets/export.py
geecomposite/widgets/manager.py
geecomposite/widgets/map.py
geecomposite/widgets/scores.py
geecomposite/widgets/season.py
geecomposite/widgets/site.py
geecomposite/widgets/years.py