Metadata-Version: 2.1
Name: geecomposite
Version: 0.0.1
Summary: Making Satellite images composites using Google Earth Engine Python API
Home-page: UNKNOWN
Author: Rodrigo E. Principe
Author-email: fitoprincipe82@gmail.com
License: MIT
Keywords: google earth engine raster image processing gis satelite
Platform: UNKNOWN
Classifier: Programming Language :: Python :: 2
Classifier: Programming Language :: Python :: 2.7
Classifier: Programming Language :: Python :: 3
Classifier: Programming Language :: Python :: 3.3
Classifier: Programming Language :: Python :: 3.4
Classifier: Programming Language :: Python :: 3.5
Classifier: License :: OSI Approved :: MIT License
Provides-Extra: dev
Provides-Extra: docs
Provides-Extra: testing
